{
  "sessionName": "a1-erp-hy-wave10",
  "baseRef": "origin/main",
  "launcherCommand": "bash {repo_root}/scripts/orchestrate-codex-worker.sh {task_file} {handoff_file} {status_file} {worktree_path} {worker_name}",
  "workers": [
    {
      "name": "purchase-reorder-suggester",
      "task": "Phase 2 Purchasing — Reorder suggester. Wire stock_shortages (added in Wave 9) to purchase_orders via a reorder_suggestions table. The flow: a shortage is recorded, the suggester picks the best vendor from purchase_vendor_prices, the Purchaser accepts the suggestion, the system creates a draft PO in one call.\n\nSCOPE:\n1. Add `reorder_suggestions` table (db.js, append after the Wave 9 stock_shortages section):\n   - id INTEGER PK\n   - org_id INTEGER NOT NULL\n   - shortage_id INTEGER NOT NULL REFERENCES stock_shortages(id)\n   - suggested_vendor_id INTEGER REFERENCES purchase_vendors(id)\n   - suggested_unit_cost REAL\n   - suggested_quantity REAL\n   - currency TEXT DEFAULT 'AMD'\n   - status TEXT NOT NULL CHECK (status IN ('pending','accepted','rejected','expired')) DEFAULT 'pending'\n   - created_purchase_order_id INTEGER REFERENCES purchase_orders(id)\n   - created_at TEXT DEFAULT CURRENT_TIMESTAMP\n   - resolved_at TEXT\n2. Add `GET /api/purchase/reorder-suggestions?status=pending` endpoint. Pre-handler: `requirePerm('purchase.analytics.read')` — already registered.\n3. Add `POST /api/purchase/reorder-suggestions/:id/accept` endpoint. Pre-handler: `requirePerm('purchase.po.create')` — already registered. Body: `{ vendor_id?, quantity?, unit_cost? }`. The system creates a purchase_orders row (status='draft') with one purchase_order_lines row referencing the shortage's item_id, then sets the suggestion's status='accepted' and created_purchase_order_id.\n4. Add `POST /api/purchase/reorder-suggestions/:id/reject` endpoint. Pre-handler: `requirePerm('purchase.po.create')`. Body: `{ reason }`. Sets status='rejected' and resolved_at.\n5. Create `server/purchasing/reorder-suggester.js` with the picker engine. Pure functions:\n   - `pickBestVendor(prices, itemId, quantity)` — returns `{ vendorId, unitCost, currency } | null`\n   - `suggestionToPoBody(suggestion, shortage)` — returns `{ vendor_id, lines: [{ item_id, quantity, unit_cost }] }`\n6. (Optional bonus) A cron-style helper at `server/purchasing/auto-suggest.js` that, given a shortage, auto-creates a pending suggestion row. Not exposed as a route — just a callable function the Wave 9 sales-order hook can call.\n\nCONSTRAINTS:\n- Touch only: server/db.js (append CREATE TABLE), server/app.js (3 new routes), server/purchasing/reorder-suggester.js (new), server/purchasing/auto-suggest.js (new, optional), server/rbac/permissions.js (only if a perm is missing — none should be).\n- Do NOT touch Wave 9's stock_shortages schema or any other domain's tables.\n- The new routes go in the purchase section (after the existing /api/purchase/orders/:id/bill route at line ~829).\n- Lint must stay 48/0/0/0.\n- 233/233 existing api tests must still pass.\n\nVERIFICATION:\n1. `node scripts/lint-rbac-broad-grants.js` — still 48/0/0/0\n2. `node --test test/api.test.js 2>&1 | tail -5` — 233/233\n3. Add 8+ tests in test/purchase-reorder-suggester.test.js covering: best vendor picker (lowest price), fallback to most-recent vendor, suggestion-to-PO body shape, accept creates PO, reject transitions status, list filters by status\n\nDELIVERABLE: One commit titled `Wave 10: Phase 2 Purchasing — reorder suggester (shortage → PO)`. Push. Write handoff.md."
    },
    {
      "name": "purchase-three-way-match",
      "task": "Phase 2 Purchasing — Three-way match. Compare the ordered qty (purchase_order_lines), the received qty (in the same line, updated by receivePurchaseOrder), and the billed qty. Mismatches become alertable rows. The Purchaser/Accountant sees the matches and resolves the gaps.\n\nSCOPE:\n1. Add `po_receipt_matches` table (db.js, append after the reorder_suggestions section):\n   - id INTEGER PK\n   - purchase_order_id INTEGER NOT NULL REFERENCES purchase_orders(id)\n   - purchase_order_line_id INTEGER NOT NULL REFERENCES purchase_order_lines(id)\n   - ordered_qty REAL NOT NULL\n   - received_qty REAL NOT NULL\n   - variance_qty REAL NOT NULL  (received - ordered)\n   - status TEXT NOT NULL CHECK (status IN ('matched','under_received','over_received'))\n   - created_at TEXT DEFAULT CURRENT_TIMESTAMP\n2. Add `po_bill_matches` table:\n   - id INTEGER PK\n   - purchase_order_id INTEGER NOT NULL REFERENCES purchase_orders(id)\n   - purchase_order_line_id INTEGER NOT NULL REFERENCES purchase_order_lines(id)\n   - ordered_unit_cost REAL NOT NULL\n   - billed_unit_cost REAL NOT NULL\n   - variance_pct REAL NOT NULL\n   - status TEXT NOT NULL CHECK (status IN ('matched','price_increase','price_decrease'))\n   - created_at TEXT DEFAULT CURRENT_TIMESTAMP\n3. If `purchase_order_lines.received_qty` column doesn't exist, ALTER TABLE to add it (check first). It SHOULD already be there from earlier work — if not, default it to 0 for existing rows.\n4. Add `GET /api/purchase/orders/:id/match` endpoint. Pre-handler: `requirePerm('purchase.po.read')`. Returns the latest receipt + bill matches for the order.\n5. Add `POST /api/purchase/orders/:id/match/recompute` endpoint. Pre-handler: `requirePerm('purchase.po.update')`. Server recomputes the matches from current line state and writes new po_receipt_matches + po_bill_matches rows.\n6. Add `GET /api/purchase/matches/receipts?variance_min=0.05` endpoint. Pre-handler: `requirePerm('purchase.analytics.read')`. Lists lines with |variance_qty / ordered_qty| >= variance_min.\n7. Add `GET /api/purchase/matches/bills?variance_min=0.05` endpoint. Pre-handler: `requirePerm('purchase.analytics.read')`. Lists lines with |variance_pct| >= variance_min.\n8. Create `server/purchasing/three-way-match.js` with the comparison engine. Pure functions:\n   - `matchReceipt(orderedQty, receivedQty, tolerance = 0.01)` → `{ variance, status: 'matched'|'under_received'|'over_received' }`\n   - `matchPrice(orderedUnitCost, billedUnitCost, tolerance = 0.01)` → `{ variancePct, status: 'matched'|'price_increase'|'price_decrease' }`\n\nCONSTRAINTS:\n- Touch only: server/db.js (append 2 new tables + maybe 1 ALTER), server/app.js (4 new routes), server/purchasing/three-way-match.js (new), server/rbac/permissions.js (no new perms needed).\n- Do NOT modify the purchase_orders / purchase_order_lines schema beyond the received_qty ALTER.\n- Do NOT modify the receivePurchaseOrder or billPurchaseOrder handlers in this wave (that's a Wave 11+ job — this wave just adds the read + recompute endpoints so matches are visible and re-runnable on demand).\n- The new routes go in the purchase section (after the existing /api/purchase/orders/:id/bill route at line ~829, or after Worker A's reorder routes if they're in the same worktree).\n- Lint must stay 48/0/0/0.\n- 233/233 existing api tests must still pass.\n\nVERIFICATION:\n1. `node scripts/lint-rbac-broad-grants.js` — still 48/0/0/0\n2. `node --test test/api.test.js 2>&1 | tail -5` — 233/233\n3. Add 8+ tests in test/purchase-three-way-match.test.js covering: matchReceipt tolerance, matchPrice tolerance, status thresholds, recompute writes rows, list filters by variance_min, GET /match returns the latest row per line\n\nDELIVERABLE: One commit titled `Wave 10: Phase 2 Purchasing — three-way match (PO ↔ receipt ↔ bill)`. Push. Write handoff.md."
    },
    {
      "name": "purchase-vendor-360",
      "task": "Phase 2 Purchasing — Vendor 360 dashboard. A read-only view that composes vendor info + recent POs + open receipts + open bills + open reorder suggestions into a single per-vendor summary. No schema changes.\n\nSCOPE:\n1. Add `GET /api/purchase/vendors/:id/360` endpoint. Pre-handler: `requirePerm('purchase.vendor_360.read')` — already registered. Returns: vendor info + count of open POs + count of open receipts + total spend YTD + last PO date + count of open reorder suggestions + list of recent POs (last 5).\n2. Add `GET /api/purchase/vendors/:id/recent-orders` endpoint. Pre-handler: `requirePerm('purchase.po.read')`. Returns: last 10 POs for the vendor with id, status, total, created_at.\n3. Add `GET /api/purchase/vendors/:id/price-history` endpoint. Pre-handler: `requirePerm('purchase.pricelist.read')`. Returns: most recent 20 rows from purchase_vendor_prices for this vendor with item info.\n4. Create `server/purchasing/vendor-360.js` with the aggregation function. Pure function:\n   - `buildVendor360(vendor, pos, receipts, bills, suggestions)` → returns the 360 object the route serializes. No DB calls inside.\n\nCONSTRAINTS:\n- Touch ONLY: server/app.js (3 new routes in the purchase section) and server/purchasing/vendor-360.js (new).\n- Do NOT modify any schema, db.js, or other domain code.\n- All 3 perm keys (`purchase.vendor_360.read`, `purchase.po.read`, `purchase.pricelist.read`) are already registered.\n- The new routes go in the purchase section (after the existing /api/purchase/orders/:id/bill route at line ~829, or after the Wave 10 reorder + three-way-match routes if they're in the same worktree).\n- Lint must stay 48/0/0/0.\n- 233/233 existing api tests must still pass.\n\nVERIFICATION:\n1. `node scripts/lint-rbac-broad-grants.js` — still 48/0/0/0\n2. `node --test test/api.test.js 2>&1 | tail -5` — 233/233\n3. Add 8+ tests in test/purchase-vendor-360.test.js covering: buildVendor360 happy path with sample data, recent-orders shape, price-history shape, perm-required enforcement (403 without purchase.vendor_360.read)\n\nDELIVERABLE: One commit titled `Wave 10: Phase 2 Purchasing — Vendor 360 dashboard`. Push. Write handoff.md."
    }
  ]
}
